[
  {
    "src": [
      "../video/Video1.ogg",
      "../video/Video1.webm"
    ],
    "img": "../graphics/VideoThumNail/Snapshot_Video1.png",
    "title": "Two and Half Men 1"
  },
  {
    "src": [
      "../video/Video2.ogg",
      "../video/Video2.webm"
    ],
    "img": "../graphics/VideoThumNail/Snapshot_Video2.png",
    "title": "Two and Half Men 2"
  },
  {
    "src": [
      "../video/Video3.ogg",
      "../video/Video3.webm"
    ],
    "img": "../graphics/VideoThumNail/Snapshot_Video3.png",
    "title": "Two and Half Men 3"
  },
  {
    "src": [
      "../video/Video4.ogg",
      "../video/Video4.webm"
    ],
    "img": "../graphics/VideoThumNail/Snapshot_Video4.png",
    "title": "Two and Half Men 4"
  }
]